LICENSE
README.md
setup.py
ranyutest.egg-info/PKG-INFO
ranyutest.egg-info/SOURCES.txt
ranyutest.egg-info/dependency_links.txt
ranyutest.egg-info/top_level.txt
wrtestpypi/__init__.py
wrtestpypi/test.py